semfarm/__init__.py
semfarm/__main__.py
semfarm/api.py
semfarm/cli.py
semfarm/py.typed
semfarm/version.py
semfarm-0.0.1.dist-info/licenses/LICENSE
semfarm-0.0.1.dist-info/WHEEL
semfarm-0.0.1.dist-info/entry_points.txt
semfarm-0.0.1.dist-info/METADATA
semfarm-0.0.1.dist-info/RECORD
